<?xml version="1.0" encoding="UTF-8"?>
<!DOCTYPE mapper PUBLIC "-//mybatis.org//DTD Mapper 3.0//EN" "http://mybatis.org/dtd/mybatis-3-mapper.dtd">
<mapper namespace="com.cheers.dao.ClothDOMapper">
  <resultMap id="BaseResultMap" type="com.cheers.dataobject.ClothDO">
    <!--
      WARNING - @mbg.generated
      This element is automatically generated by MyBatis Generator, do not modify.
      This element was generated on Thu May 25 00:18:11 CST 2023.
    -->
    <id column="id" jdbcType="INTEGER" property="id" />
    <result column="imgUrl" jdbcType="VARCHAR" property="imgUrl" />
    <result column="price" jdbcType="DECIMAL" property="price" />
    <result column="year" jdbcType="VARCHAR" property="year" />
    <result column="comment" jdbcType="VARCHAR" property="comment" />
  </resultMap>
  <sql id="Base_Column_List">
    <!--
      WARNING - @mbg.generated
      This element is automatically generated by MyBatis Generator, do not modify.
      This element was generated on Thu May 25 00:18:11 CST 2023.
    -->
    id, imgUrl, price, year, comment
  </sql>
  <select id="selectByPrimaryKey" parameterType="java.lang.Integer" resultMap="BaseResultMap">
    <!--
      WARNING - @mbg.generated
      This element is automatically generated by MyBatis Generator, do not modify.
      This element was generated on Thu May 25 00:18:11 CST 2023.
    -->
    select 
    <include refid="Base_Column_List" />
    from cloth
    where id = #{id,jdbcType=INTEGER}
  </select>
  <delete id="deleteByPrimaryKey" parameterType="java.lang.Integer">
    <!--
      WARNING - @mbg.generated
      This element is automatically generated by MyBatis Generator, do not modify.
      This element was generated on Thu May 25 00:18:11 CST 2023.
    -->
    delete from cloth
    where id = #{id,jdbcType=INTEGER}
  </delete>
  <insert id="insert" parameterType="com.cheers.dataobject.ClothDO">
    <!--
      WARNING - @mbg.generated
      This element is automatically generated by MyBatis Generator, do not modify.
      This element was generated on Thu May 25 00:18:11 CST 2023.
    -->
    insert into cloth (id, imgUrl, price, 
      year, comment)
    values (#{id,jdbcType=INTEGER}, #{imgUrl,jdbcType=VARCHAR}, #{price,jdbcType=DECIMAL},
      #{year,jdbcType=VARCHAR}, #{comment,jdbcType=VARCHAR})
  </insert>
  <insert id="insertSelective" parameterType="com.cheers.dataobject.ClothDO">
    <!--
      WARNING - @mbg.generated
      This element is automatically generated by MyBatis Generator, do not modify.
      This element was generated on Thu May 25 00:18:11 CST 2023.
    -->
    insert into cloth
    <trim prefix="(" suffix=")" suffixOverrides=",">
      <if test="id != null">
        id,
      </if>
      <if test="imgUrl != null">
        imgUrl,
      </if>
      <if test="price != null">
        price,
      </if>
      <if test="year != null">
        year,
      </if>
      <if test="comment != null">
        comment,
      </if>
    </trim>
    <trim prefix="values (" suffix=")" suffixOverrides=",">
      <if test="id != null">
        #{id,jdbcType=INTEGER},
      </if>
      <if test="imgUrl != null">
        #{imgUrl,jdbcType=VARCHAR},
      </if>
      <if test="price != null">
        #{price,jdbcType=DECIMAL},
      </if>
      <if test="year != null">
        #{year,jdbcType=VARCHAR},
      </if>
      <if test="comment != null">
        #{comment,jdbcType=VARCHAR},
      </if>
    </trim>
  </insert>
  <update id="updateByPrimaryKeySelective" parameterType="com.cheers.dataobject.ClothDO">
    <!--
      WARNING - @mbg.generated
      This element is automatically generated by MyBatis Generator, do not modify.
      This element was generated on Thu May 25 00:18:11 CST 2023.
    -->
    update cloth
    <set>
      <if test="imgUrl != null">
        imgUrl = #{imgUrl,jdbcType=VARCHAR},
      </if>
      <if test="price != null">
        price = #{price,jdbcType=DECIMAL},
      </if>
      <if test="year != null">
        year = #{year,jdbcType=VARCHAR},
      </if>
      <if test="comment != null">
        comment = #{comment,jdbcType=VARCHAR},
      </if>
    </set>
    where id = #{id,jdbcType=INTEGER}
  </update>
  <update id="updateByPrimaryKey" parameterType="com.cheers.dataobject.ClothDO">
    <!--
      WARNING - @mbg.generated
      This element is automatically generated by MyBatis Generator, do not modify.
      This element was generated on Thu May 25 00:18:11 CST 2023.
    -->
    update cloth
    set imgUrl = #{imgUrl,jdbcType=VARCHAR},
      price = #{price,jdbcType=DECIMAL},
      year = #{year,jdbcType=VARCHAR},
      comment = #{comment,jdbcType=VARCHAR}
    where id = #{id,jdbcType=INTEGER}
  </update>
</mapper>